{
    "Admin":{
        "add_photo":true,
        "open_photo_location":true,
        "item_name":true,
        "manufacturer":true,
        "item_location":true,
        "quantity":true,
        "quantit_per_package":true,
        "supplier":true,
        "distributor":true,
        "more_info":true,
        "keywords":true,
        "msds_path":true,
        "upload_msds":true,
        "open_msds_in_folder":true,
        "prohibition":true,
        "warning":true,
        "mandatory":true,
        "emergency":true,
        "firefighting":true,
        "chemical":true,
        "configuration":true,
        "initialisation":true,
        "profiles":true,
        "style":true
    },
    "User":{
        "add_photo":false,
        "open_photo_location":false,
        "item_name":true,
        "manufacturer":true,
        "item_location":true,
        "quantity":true,
        "quantit_per_package":true,
        "supplier":true,
        "distributor":true,
        "more_info":true,
        "keywords":true,
        "msds_path":true,
        "upload_msds":true,
        "open_msds_in_folder":true,
        "prohibition":true,
        "warning":true,
        "mandatory":true,
        "emergency":true,
        "firefighting":true,
        "chemical":true,
        "configuration":true,
        "initialisation":true,
        "profiles":false,
        "style":true
    },
    "Guest":{
        "add_photo":false,
        "open_photo_location":false,
        "item_name":false,
        "manufacturer":false,
        "item_location":false,
        "quantity":false,
        "quantit_per_package":false,
        "supplier":false,
        "distributor":false,
        "more_info":false,
        "keywords":false,
        "msds_path":false,
        "upload_msds":false,
        "open_msds_in_folder":false,
        "prohibition":false,
        "warning":false,
        "mandatory":false,
        "emergency":false,
        "firefighting":false,
        "chemical":false,
        "configuration":false,
        "initialisation":false,
        "profiles":false,
        "style":false
    }

}